README.md
setup.py
alibabacloud_eventbridge/__init__.py
alibabacloud_eventbridge/client.py
alibabacloud_eventbridge/models.py
alibabacloud_eventbridge.egg-info/PKG-INFO
alibabacloud_eventbridge.egg-info/SOURCES.txt
alibabacloud_eventbridge.egg-info/dependency_links.txt
alibabacloud_eventbridge.egg-info/requires.txt
alibabacloud_eventbridge.egg-info/top_level.txt